aioamqp/__init__.py
aioamqp/channel.py
aioamqp/compat.py
aioamqp/constants.py
aioamqp/envelope.py
aioamqp/exceptions.py
aioamqp/frame.py
aioamqp/properties.py
aioamqp/protocol.py
aioamqp/version.py
aioamqp-0.15.0.dist-info/AUTHORS.rst
aioamqp-0.15.0.dist-info/LICENSE
aioamqp-0.15.0.dist-info/METADATA
aioamqp-0.15.0.dist-info/WHEEL
aioamqp-0.15.0.dist-info/top_level.txt
aioamqp-0.15.0.dist-info/RECORD
