Metadata-Version: 2.1
Name: aioamqp
Version: 0.15.0
Summary: AMQP implementation using asyncio
Home-page: https://github.com/polyconseil/aioamqp
Download-URL: https://pypi.python.org/pypi/aioamqp
Author: Polyconseil dev' team
Author-email: opensource+aioamqp@polyconseil.fr
License: BSD
Keywords: asyncio,amqp,rabbitmq,aio
Platform: all
Classifier: Development Status :: 4 - Beta
Classifier: Intended Audience :: Developers
Classifier: License :: OSI Approved :: BSD License
Classifier: Operating System :: OS Independent
Classifier: Programming Language :: Python
Classifier: Programming Language :: Python :: 3
Classifier: Programming Language :: Python :: 3.7
Classifier: Programming Language :: Python :: 3.8
Classifier: Programming Language :: Python :: 3.9
Classifier: Programming Language :: Python :: 3.10
Requires-Python: >=3.7
License-File: LICENSE
License-File: AUTHORS.rst
